{
  "notFound": {
    "title": "404 Page Not Found",
    "body": {
      "text1": "お探しのページが見つかりませんでした",
      "text2": "お探しのページは、削除または移動されたか、一時的に利用できない可能性があります。",
      "text3": "直接アドレスを入力された場合は、入力内容が正しいか今一度ご確認ください。",
      "text4": "ブラウザの再読み込みを行ってもこのページが表示される場合は、お手数をおかけしますが",
      "text5": "へ戻るか、各メニューのリンクから目的のページをお探しください。"
    }
  },
  "serverError": {
    "title": "500 Page Server error",
    "body": {
      "text1": "申し訳ございません。サーバーエラーが発生しました。",
      "text2": "お手数ですが、以下のいずれかの方法をお試しください。",
      "text3": "しばらく経っても解決しない場合は、<a class='serverError__menu_link' href='/contact'>お問い合わせフォーム</a>よりご連絡ください。"
    },
    "menu": [
      {
        "href": "/",
        "ariaLabel": "トップページへ戻る",
        "ariaTitle": "トップページへ戻る",
        "text": "トップページ",
        "textAfter": "へ戻る"
      },
      {
        "href": "/contact",
        "ariaLabel": "お問い合わせページへ",
        "ariaTitle": "お問い合わせページへ",
        "text": "お問い合わせ",
        "textAfter": "はこちらから"
      }
    ]
  },
  "sorry": {
    "title": "すいません。このページは準備中です。",
    "body": [
      {
        "text": "当サイトをご覧いただきありがとうございます。"
      },
      {
        "text": "各ページは随時更新しております。しばらくお待ちください。"
      }
    ],
    "imageAlt": "開発中のため立ち入り禁止する猫の画像",
    "link": "<a class='sorry__link' href='/'> トップページ</a>に戻る"
  }
}
